{
	"name": "ESPN Final Round Golf 2002",
	"description": "Golf action has moved from the greens to the portable convenience of the Game Boy&reg; Advance. Choose from 14 golfers, 5 courses and a variety of club. You will experience realistic weather conditions such as wind, rain and sunshine on the fairway. Tee off against up to 3 other players using the Game Boy&reg; Advance Game Link&reg; cable.",
	"released": "Aug 28, 2001",
	"developer": "Konami Computer Entertainment Nagoya",
	"genre": "Sports, Traditional, Golf, Sim",
	"cover": "https://andr3carvalh0.github.io/mGBA_Database/Covers/15080_front.jpg"
}
