{
	"name": "NSYNC: Get to the Show",
	"description": "You're on the road with the #1 band in America and there's a lot to do before a show!With the NSYNC Get to the Show game, it's your job to keep the band happy by helping them get ready for the big night.Grab the keys to the limo and run errands, keep hotel guests quiet so the guys can get a good night's sleep, make their favorite burgers and even play a quick game of hackey sack to warm up before the show!And just like regular guys, the band has errands they need to do too!Take them to the post office, gym or florist and help them get it all done!",
	"released": "Dec 12, 2001",
	"developer": "Stunt Puppy Entertainment, Inc.",
	"genre": "Action, General",
	"cover": "https://andr3carvalh0.github.io/mGBA_Database/Covers/27038_front.jpg"
}
