{
	"name": "Curious George",
	"description": "The Man with the Yellow Hat sets out on a journey to Africa in hopes of finding an artifact exotic enough to save the museum where he works. George, a curious little monkey with an insatiable taste for adventure, follows the Man with the Yellow Hat back to the big city where his spunky and fun-loving nature endears him to new friends he meets along the way and lands him in a series of mis-adventures. Guide George through a variety of adventure-packed levels based on the Universal Pictures and Imagine Entertainment animated feature film, Curious George. Explore, solve puzzles, collect items and above all, be curious! Meet and greet your favorite movie characters, unlock special mini-games and more. Loads of bonus content will keep you playing long after the main quest is solved.",
	"released": "Feb1, 2006",
	"developer": "Torus Games",
	"genre": "Action Adventure, Fantasy",
	"cover": "https://andr3carvalh0.github.io/mGBA_Database/Covers/70760_front.jpg"
}
