{
	"name": "Chicken Run",
	"description": "Behind the barbed wire fence of Tweedy Farm, Ginger is a chicken with a mission. Fearing for the lives of her friends, she is determined to escape to freedom before it is too late. To do this she enlists the help of Rocky, the smooth talking, flying Rooster...or is he?Guide a rescue attempt to get all of the chickens to safety before they end up as pies. To do this you will have to sneak around the farm collecting objects necessary for the escape. Be careful not to disturb the dogs and avoid being caught by Mr. and Mrs. Tweedy at all costs in this humorous, 3D action game.",
	"released": "November 2000",
	"developer": "Blitz Games",
	"genre": "Action, General",
	"cover": "https://andr3carvalh0.github.io/mGBA_Database/Covers/10624_front.jpg"
}
