{
	"name": "Pocket Monsters: Ao",
	"description": "You've finally been granted your Pok&eacute;mon trainer's license. Now, it's time to head out to become the world's greatest Pok&eacute;mon trainer. It's going to take all you've got to collect 150 Pok&eacute;mon in this enormous world. Catch and train monsters like the shockingly-cute Pikachu. Face off against Blastoise's torrential water cannons. Stand strong when facing Pidgeot's stormy Gust. Trade with friends and watch your Pok&eacute;mon evolve. Important--no single Pok&eacute;mon can win it all. Can you develop the ultimate Pok&eacute;mon strategy to defeat the eight GYM Leaders and become the greatest Pok&eacute;mon Master of all time?",
	"released": "Sep 30, 1998",
	"developer": "Game Freak",
	"genre": "Role-Playing, Console-style RPG",
	"cover": "https://andr3carvalh0.github.io/mGBA_Database/Covers/821_front.jpg"
}
