{
	"name": "The Jungle Book",
	"description": "Get down to the bare necessities of life... and escort Mowgli through the jungle to the safety of the human village. Fight the boggle-eyed snake, Kaa, and defeat Shere Khan the hungry tiger in this exciting adventure based on Disney's classic! It'll drive you ape crazy!",
	"released": "August 1994",
	"developer": "Eurocom Entertainment Software",
	"genre": "Action, Platformer, 2D",
	"cover": "https://andr3carvalh0.github.io/mGBA_Database/Covers/31082_front.jpg"
}
